{
  "success": true,
  "results": [
    {
      "SubscrId": "141561448",
      "OrgId": "МУП \"Мостводоканал\"",
      "SubscrCode": "473673",
      "FIO": "Петров Геннадий Сергеевич",
      "Address": "ул. Производственная, д. 7, Мостовской, Краснодарский край, Россия, 352571"
    },
    {
      "SubscrId": "141561448956-2190-4",
      "OrgId": "ГУП \"ВодоканалГород\"",
      "SubscrCode": "598342",
      "FIO": "Иванова Екатерина Александровна",
      "Address": "ул. Железнодорожная, д. 15, Городской, Краснодарский край, Россия, 352590"
    }
  ]
}
