[
  {
    "PaymenId": 260792603,
    "SubscrId": "141561448",
    "Date": "20230901",
    "PostDate": "20230901",
    "Period": 202309,
    "PeriodName": "сентябрь 2023",
    "ServiceGroupName": "Теплоснабжение",
    "PaymentSource": "Интернет-банк",
    "Amount": 2800.75
  },
  {
    "PaymenId": 260792604,
    "SubscrId": "141561448",
    "Date": "20230905",
    "PostDate": "20230905",
    "Period": 202309,
    "PeriodName": "сентябрь 2023",
    "ServiceGroupName": "Водоснабжение",
    "PaymentSource": "Офис оплаты",
    "Amount": 3200.0
  },
  {
    "PaymenId": 260792605,
    "SubscrId": "141561448",
    "Date": "20231010",
    "PostDate": "20231010",
    "Period": 202310,
    "PeriodName": "октябрь 2023",
    "ServiceGroupName": "Электроснабжение",
    "PaymentSource": "Терминал оплаты",
    "Amount": 2000.0
  },
  {
    "PaymenId": 260792606,
    "SubscrId": "141561448956-2190-4",
    "Date": "20231015",
    "PostDate": "20231015",
    "Period": 202310,
    "PeriodName": "октябрь 2023",
    "ServiceGroupName": "Газоснабжение",
    "PaymentSource": "Банковский перевод",
    "Amount": 3100.25
  },
  {
    "PaymenId": 260792607,
    "SubscrId": "141561448956-2190-4",
    "Date": "20231101",
    "PostDate": "20231101",
    "Period": 202311,
    "PeriodName": "ноябрь 2023",
    "ServiceGroupName": "Канализация",
    "PaymentSource": "Мобильное приложение",
    "Amount": 1800.0
  },
  {
    "PaymenId": 260792608,
    "SubscrId": "141561448956-2190-4",
    "Date": "20231105",
    "PostDate": "20231105",
    "Period": 202311,
    "PeriodName": "ноябрь 2023",
    "ServiceGroupName": "Уборка территории",
    "PaymentSource": "Интернет-банк",
    "Amount": 2300.5
  },
  {
    "PaymenId": 260792609,
    "SubscrId": "141561448956-2190-4",
    "Date": "20231210",
    "PostDate": "20231210",
    "Period": 202312,
    "PeriodName": "декабрь 2023",
    "ServiceGroupName": "Домофон",
    "PaymentSource": "Терминал оплаты",
    "Amount": 1400.75
  },
  {
    "PaymenId": 260792610,
    "SubscrId": "141561448956-2190-4",
    "Date": "20231215",
    "PostDate": "20231215",
    "Period": 202312,
    "PeriodName": "декабрь 2023",
    "ServiceGroupName": "Интернет",
    "PaymentSource": "Офис оплаты",
    "Amount": 2000.0
  },
  {
    "PaymenId": 260792611,
    "SubscrId": "141561448956-2190-4",
    "Date": "20240101",
    "PostDate": "20240101",
    "Period": 202401,
    "PeriodName": "январь 2024",
    "ServiceGroupName": "Теплоснабжение",
    "PaymentSource": "Банковский перевод",
    "Amount": 2700.25
  },
  {
    "PaymenId": 260792612,
    "SubscrId": "141561448956-2190-4",
    "Date": "20240105",
    "PostDate": "20240105",
    "Period": 202401,
    "PeriodName": "январь 2024",
    "ServiceGroupName": "Водоснабжение",
    "PaymentSource": "Интернет-банк",
    "Amount": 3100.0
  },
  {
    "PaymenId": 260792613,
    "SubscrId": "141561448956-2190-4",
    "Date": "20240210",
    "PostDate": "20240210",
    "Period": 202402,
    "PeriodName": "февраль 2024",
    "ServiceGroupName": "Электроснабжение",
    "PaymentSource": "Терминал оплаты",
    "Amount": 1900.0
  },
  {
    "PaymenId": 260792614,
    "SubscrId": "141561448956-2190-4",
    "Date": "20240215",
    "PostDate": "20240215",
    "Period": 202402,
    "PeriodName": "февраль 2024",
    "ServiceGroupName": "Газоснабжение",
    "PaymentSource": "Банковский перевод",
    "Amount": 3000.25
  },
  {
    "PaymenId": 260792615,
    "SubscrId": "141561448",
    "Date": "20240301",
    "PostDate": "20240301",
    "Period": 202403,
    "PeriodName": "март 2024",
    "ServiceGroupName": "Канализация",
    "PaymentSource": "Мобильное приложение",
    "Amount": 1700.0
  },
  {
    "PaymenId": 260792616,
    "SubscrId": "141561448",
    "Date": "20240305",
    "PostDate": "20240305",
    "Period": 202403,
    "PeriodName": "март 2024",
    "ServiceGroupName": "Уборка территории",
    "PaymentSource": "Интернет-банк",
    "Amount": 2100.5
  }
]